[
  {
    "id": 1,
    "topic": "Malaria Vaccine R21",
    "category": "Medical",
    "reward": 500,
    "description": "Verify claims about the efficacy and rollout of the new R21 malaria vaccine compared to existing treatments."
  },
  {
    "id": 2,
    "topic": "Lagos-Abuja Tunnel",
    "category": "Political",
    "reward": 250,
    "description": "Investigate claims surrounding the construction and operational status of a high-speed rail tunnel between Lagos and Abuja."
  },
  {
    "id": 3,
    "topic": "Climate Change",
    "category": "Science",
    "reward": 750,
    "description": "Analyze AI-generated content discussing the primary drivers of climate change, focusing on anthropogenic vs. natural causes."
  }
]
